<?xml version="1.0"?>
<objects>
<!-- ('', 'zport', 'dmd', 'Devices', 'Server', 'Synology') -->
<object id='/zport/dmd/Devices/Server/Synology' module='Products.ZenModel.DeviceClass' class='DeviceClass'>
<property visible="True" label="Collector Plugins" type="lines" description="" id="zCollectorPlugins" >
['zenoss.snmp.DeviceMap', 'zenoss.snmp.InterfaceMap', 'zenoss.snmp.RouteMap', 'zenoss.snmp.IpServiceMap', 'zenoss.snmp.HRFileSystemMap', 'zenoss.snmp.HRSWRunMap', 'zenoss.snmp.CpuMap', 'community.snmp.SynologyDeviceMap', 'community.snmp.SynologySystemMap', 'community.snmp.SynologyHardDiskMap', 'community.snmp.SynologyLogicalDiskMap']
</property>
</object>
<!-- ('', 'zport', 'dmd', 'Events', 'Status', 'HardDisk') -->
<object id='/zport/dmd/Events/Status/HardDisk' module='Products.ZenEvents.EventClass' class='EventClass'>
</object>
<!-- ('', 'zport', 'dmd', 'Events', 'Status', 'RAID') -->
<object id='/zport/dmd/Events/Status/RAID' module='Products.ZenEvents.EventClass' class='EventClass'>
</object>
<!-- ('', 'zport', 'dmd', 'Events', 'Status', 'System') -->
<object id='/zport/dmd/Events/Status/System' module='Products.ZenEvents.EventClass' class='EventClass'>
</object>
</objects>
